LICENSE
MANIFEST.in
README.rst
setup.py
Mopidy_Subsonic.egg-info/PKG-INFO
Mopidy_Subsonic.egg-info/SOURCES.txt
Mopidy_Subsonic.egg-info/dependency_links.txt
Mopidy_Subsonic.egg-info/entry_points.txt
Mopidy_Subsonic.egg-info/not-zip-safe
Mopidy_Subsonic.egg-info/requires.txt
Mopidy_Subsonic.egg-info/top_level.txt
mopidy_subsonic/__init__.py
mopidy_subsonic/actor.py
mopidy_subsonic/client.py
mopidy_subsonic/ext.conf
mopidy_subsonic/library.py
mopidy_subsonic/playlist.py