Metadata-Version: 1.1
Name: Mopidy-Subsonic
Version: 0.3.1
Summary: Subsonic extension for Mopidy
Home-page: http://github.com/rattboi/mopidy-subsonic/
Author: rattboi
Author-email: rattboi@gmail.com
License: MIT
Platform: UNKNOWN
Classifier: Environment :: No Input/Output (Daemon)
Classifier: Intended Audience :: End Users/Desktop
Classifier: License :: OSI Approved :: MIT License
Classifier: Operating System :: OS Independent
Classifier: Programming Language :: Python :: 2
Classifier: Topic :: Multimedia :: Sound/Audio :: Players
